{
  "resource": "Contributions",
  "resource_explanation": "Contributions must be created with either an organization_ein or a portfolio_id.",
  "http_method": "POST",
  "route": "/api/v1/contributions",
  "description": "Successful request: Make a contribution to a single organization",
  "explanation": null,
  "parameters": [
    {
      "type": "string",
      "required": true,
      "name": "donor_id",
      "description": "Donor who makes the contribution"
    },
    {
      "type": "integer",
      "required": true,
      "name": "amount_cents",
      "description": "Contribution amount in cents (USD)"
    },
    {
      "type": "string",
      "required": true,
      "name": "currency",
      "description": "Contribution currency. Currently only USD is supported"
    },
    {
      "type": "string",
      "required": false,
      "name": "organization_ein",
      "description": "The tax id of the recipient charitable organization"
    },
    {
      "type": "string",
      "required": false,
      "name": "portfolio_id",
      "description": "The id of the charitable Portfolio to contribute to"
    },
    {
      "type": "string",
      "required": false,
      "name": "external_reference_id",
      "description": "The contribution id on your platform"
    }
  ],
  "response_fields": [

  ],
  "requests": [
    {
      "request_method": "POST",
      "request_path": "/api/v1/contributions",
      "request_body": "{\"contribution\":{\"donor_id\":\"f6d523db-da05-44c0-b6dd-23ec5f25ccaa\",\"amount_cents\":200,\"currency\":\"USD\",\"organization_ein\":\"org_7_802f751\",\"external_reference_id\":\"external_reference_id_1\"}}",
      "request_headers": {
        "Content-Type": "application/json",
        "X-Api-Key": "aHPNkatVdeZHE6FyQUKhlAtt",
        "Host": "example.org",
        "Cookie": ""
      },
      "request_query_parameters": {
      },
      "request_content_type": "application/json",
      "response_status": 200,
      "response_status_text": "OK",
      "response_body": "{\n  \"contribution\": {\n    \"id\": \"e6d96cf4-2897-4a72-af25-38c4d4cd30f2\",\n    \"donor_id\": \"f6d523db-da05-44c0-b6dd-23ec5f25ccaa\",\n    \"amount_cents\": 200,\n    \"scheduled_at\": \"2019-07-17T20:44:34.343Z\",\n    \"external_reference_id\": \"external_reference_id_1\",\n    \"portfolio_id\": \"95af0747-a1d1-4cc2-95d6-fdef992511a8\",\n    \"portfolio_allocations\": [\n      {\n        \"organization_ein\": \"org_7_802f751\",\n        \"percentage\": 100,\n        \"name\": \"Organization 7\"\n      }\n    ]\n  }\n}",
      "response_headers": {
        "X-Frame-Options": "SAMEORIGIN",
        "X-XSS-Protection": "1; mode=block",
        "X-Content-Type-Options": "nosniff",
        "X-Download-Options": "noopen",
        "X-Permitted-Cross-Domain-Policies": "none",
        "Referrer-Policy": "strict-origin-when-cross-origin",
        "Content-Type": "application/json; charset=utf-8",
        "ETag": "W/\"0c6143db27a19a2948eab1f5c27ec1bc\"",
        "Cache-Control": "max-age=0, private, must-revalidate",
        "X-Request-Id": "b9103405-f0e2-44b6-961c-564a8c0bbd1d",
        "X-Runtime": "0.037596",
        "Content-Length": "381"
      },
      "response_content_type": "application/json; charset=utf-8",
      "curl": null
    }
  ]
}